{
  "$schema": "https://mintlify.com/schema.json",
  "name": "Omnifuel AI - Documentation",
  "logo": {
    "dark": "/logo/dark.svg",
    "light": "/logo/light.svg"
  },
  "favicon": "/favicon.svg",
  "colors": {
    "primary": "#0D9373",
    "light": "#07C983",
    "dark": "#0D9373",
    "anchors": {
      "from": "#0D9373",
      "to": "#07C983"
    }
  },
  "topbarLinks": [
    {
      "name": "Support",
      "url": "mailto:support@omnifuel.ai"
    }
  ],
  "topbarCtaButton": {
    "name": "Dashboard",
    "url": "https://www.omnifuel.ai"
  },
  "tabs": [
    {
      "name": "API Reference",
      "url": "api-reference"
    }
  ],
  "anchors": [],
  "navigation": [
    {
      "group": "Get Started",
      "pages": [
        "introduction",
        "architecture",
        "models"
      ]
    },
    {
      "group": "API Documentation",
      "pages": [
        "api-reference/introduction"
      ]
    },
    {
      "group": "Forecaster",
      "pages": [
        "api-reference/forecaster/train-a-forecaster",
        "api-reference/forecaster/get-forecaster",
        "api-reference/forecaster/generate-forecast"
      ]
    }
  ],
  "footerSocials": {}
}